chaya/__init__.py
chaya/chaya.py
chaya-ml/__init__.py
chaya-ml/chaya-ml.py
chaya_ai/__init__.py
chaya_ai/chaya_ai.py
distml/__init__.py
distml/distml_logger.py
distml_logger/__init__.py
distml_logger/distml_logger.py
dlog/__init__.py
dlog/distml_logger.py
chaya_ai-0.1.7.dist-info/LICENSE.txt
chaya_ai-0.1.7.dist-info/METADATA
chaya_ai-0.1.7.dist-info/WHEEL
chaya_ai-0.1.7.dist-info/top_level.txt
chaya_ai-0.1.7.dist-info/RECORD
