Metadata-Version: 2.1
Name: chaya-ai
Version: 0.1.7
Summary: chaya-ai
Home-page: https://app.chaya.ai/
Author: Chaya-ML Dev
Author-email: <sundi@chaya.ai>
License: MIT
Download-URL: https://storage.googleapis.com/chaya-assets/chaya_ai-0.0.8.tar.gz
Keywords: python,chaya-ai
Platform: UNKNOWN
Classifier: Development Status :: 4 - Beta
Classifier: Intended Audience :: Developers
Classifier: Topic :: Software Development :: Build Tools
Classifier: License :: OSI Approved :: MIT License
Classifier: Programming Language :: Python :: 3
Classifier: Programming Language :: Python :: 3.4
Classifier: Programming Language :: Python :: 3.5
Classifier: Programming Language :: Python :: 3.6
License-File: LICENSE.txt
Requires-Dist: aiohttp
Requires-Dist: asyncio
Requires-Dist: requests
Requires-Dist: pybase64
Requires-Dist: dbutils
Requires-Dist: iplotter
Requires-Dist: tabulate
Requires-Dist: pandas
Requires-Dist: ipyparams (==0.2.1)
